pyscal/__init__.py
pyscal/__version__.py
pyscal/constants.py
pyscal/factory.py
pyscal/gasoil.py
pyscal/gaswater.py
pyscal/plotting.py
pyscal/py.typed
pyscal/pyscal_logger.py
pyscal/pyscalcli.py
pyscal/pyscallist.py
pyscal/scalrecommendation.py
pyscal/version.py
pyscal/wateroil.py
pyscal/wateroilgas.py
pyscal/utils/__init__.py
pyscal/utils/capillarypressure.py
pyscal/utils/interpolation.py
pyscal/utils/monotonicity.py
pyscal/utils/relperm.py
pyscal/utils/string.py
pyscal-0.15.3.dist-info/licenses/LICENSE
pyscal-0.15.3.dist-info/METADATA
pyscal-0.15.3.dist-info/WHEEL
pyscal-0.15.3.dist-info/entry_points.txt
pyscal-0.15.3.dist-info/top_level.txt
pyscal-0.15.3.dist-info/RECORD
