Metadata-Version: 2.4
Name: pyscal
Version: 0.15.3
Summary: Generate relative permeability include files for Eclipse reservoir simulator
Author-email: Håvard Berland <havb@equinor.com>
License-Expression: LGPL-3.0-or-later
Project-URL: Homepage, https://github.com/equinor/pyscal
Project-URL: Documentation, https://equinor.github.io/pyscal/
Project-URL: Repository, https://github.com/equinor/pyscal
Keywords: relative permeability,capillary pressure,reservoir simulation
Classifier: Development Status :: 5 - Production/Stable
Classifier: Intended Audience :: Science/Research
Classifier: Topic :: Scientific/Engineering
Classifier: Topic :: Scientific/Engineering :: Physics
Classifier: Topic :: Software Development :: Libraries
Classifier: Topic :: Utilities
Classifier: Programming Language :: Python :: 3.11
Classifier: Programming Language :: Python :: 3.12
Classifier: Programming Language :: Python :: 3.13
Classifier: Programming Language :: Python :: 3.14
Classifier: Natural Language :: English
Requires-Python: >=3.11
License-File: LICENSE
Requires-Dist: matplotlib
Requires-Dist: numpy
Requires-Dist: openpyxl
Requires-Dist: pandas
Requires-Dist: scipy
Requires-Dist: xlrd
Provides-Extra: tests
Requires-Dist: ruff; extra == "tests"
Requires-Dist: mypy; extra == "tests"
Requires-Dist: hypothesis; extra == "tests"
Requires-Dist: pytest; extra == "tests"
Requires-Dist: pytest-cov; extra == "tests"
Requires-Dist: pytest-mock; extra == "tests"
Requires-Dist: pytest-xdist; extra == "tests"
Requires-Dist: rstcheck; extra == "tests"
Requires-Dist: pandas-stubs; extra == "tests"
Requires-Dist: scipy-stubs; extra == "tests"
Provides-Extra: docs
Requires-Dist: autoapi; extra == "docs"
Requires-Dist: sphinx; extra == "docs"
Requires-Dist: sphinx-argparse; extra == "docs"
Requires-Dist: sphinx-autodoc-typehints; extra == "docs"
Requires-Dist: sphinx_rtd_theme; extra == "docs"
Dynamic: license-file
